README.md
setup.cfg
setup.py
starlette_pydantic/__init__.py
starlette_pydantic.egg-info/PKG-INFO
starlette_pydantic.egg-info/SOURCES.txt
starlette_pydantic.egg-info/dependency_links.txt
starlette_pydantic.egg-info/requires.txt
starlette_pydantic.egg-info/top_level.txt