Metadata-Version: 1.0
Name: starlette-pydantic
Version: 0.1
Summary: pydantic for starlette
Home-page: https://github.com/zpdev/starlette-pydantic
Author: zpzhou
Author-email: himoker@163.com
License: UNKNOWN
Platform: UNKNOWN
